setup.py
repoze/__init__.py
repoze.what.plugins.mongodb.egg-info/PKG-INFO
repoze.what.plugins.mongodb.egg-info/SOURCES.txt
repoze.what.plugins.mongodb.egg-info/dependency_links.txt
repoze.what.plugins.mongodb.egg-info/requires.txt
repoze.what.plugins.mongodb.egg-info/top_level.txt
repoze/what/__init__.py
repoze/what/plugins/__init__.py
repoze/what/plugins/mongodb/__init__.py
repoze/what/plugins/mongodb/adapters.py