Metadata-Version: 1.0
Name: repoze.what.plugins.mongodb
Version: 0.1.1
Summary: MongoDB adapter plugins for repoze.what
Home-page: https://bitbucket.org/rsenk330/repoze.what.plugins.mongodb/
Author: Ryan Senkbeil
Author-email: rsenk330@gmail.com
License: UNKNOWN
Platform: UNKNOWN
Classifier: Programming Language :: Python
Classifier: Development Status :: 4 - Beta
Classifier: License :: OSI Approved :: GNU General Public License (GPL)
Classifier: Operating System :: OS Independent
